tkitRetransformer/__init__.py
tkitRetransformer/tkitRetransformer.py
tkitRetransformer-0.0.0.116327477.dist-info/LICENSE
tkitRetransformer-0.0.0.116327477.dist-info/METADATA
tkitRetransformer-0.0.0.116327477.dist-info/WHEEL
tkitRetransformer-0.0.0.116327477.dist-info/top_level.txt
tkitRetransformer-0.0.0.116327477.dist-info/RECORD
