Metadata-Version: 2.1
Name: tkitRetransformer
Version: 0.0.0.116327477
Summary: Terry toolkit tkitRetransformer,
Home-page: http://docs.terrychan.org/tkit-re-transformers/
Author: Terry Chan
Author-email: napoler2008@gmail.com
License: UNKNOWN
Platform: UNKNOWN
Requires-Dist: transformers (>=4.10.0)
